kuru_sdk/__init__.py
kuru_sdk/api.py
kuru_sdk/client_order_executor.py
kuru_sdk/margin.py
kuru_sdk/orderbook.py
kuru_sdk/token.py
kuru_sdk/types.py
kuru_sdk/utils.py
kuru_sdk/websocket_handler.py
kuru_sdk/abi/ierc20.json
kuru_sdk/abi/kuruforwarder.json
kuru_sdk/abi/marginaccount.json
kuru_sdk/abi/orderbook.json
kuru_sdk-0.2.8.dist-info/licenses/LICENSE
tests/__init__.py
tests/api_tests.py
tests/client_order_exec_test.py
tests/client_test.py
tests/conftest.py
tests/test_token.py
tests/test_utils.py
kuru_sdk-0.2.8.dist-info/METADATA
kuru_sdk-0.2.8.dist-info/WHEEL
kuru_sdk-0.2.8.dist-info/top_level.txt
kuru_sdk-0.2.8.dist-info/RECORD
