Metadata-Version: 2.4
Name: kuru-sdk
Version: 0.2.8
Summary: Python SDK for Kuru's Central Limit Orderbook (CLOB)
Home-page: https://github.com/kuru/kuru-py-sdk
Author: Kuru Labs
Author-email: tech@kurulabs.xyz
Classifier: Development Status :: 3 - Alpha
Classifier: Intended Audience :: Developers
Classifier: License :: OSI Approved :: MIT License
Classifier: Operating System :: OS Independent
Classifier: Programming Language :: Python :: 3
Classifier: Programming Language :: Python :: 3.7
Classifier: Programming Language :: Python :: 3.8
Classifier: Programming Language :: Python :: 3.9
Classifier: Programming Language :: Python :: 3.10
Requires-Python: >=3.7
License-File: LICENSE
Requires-Dist: web3>=7.6.0
Requires-Dist: eth-typing>=3.5.0
Requires-Dist: eth-utils>=2.3.0
Requires-Dist: python-dotenv>=1.0.0
Requires-Dist: aiohttp>=3.9.1
Requires-Dist: python-socketio>=5.10.0
Dynamic: author
Dynamic: author-email
Dynamic: classifier
Dynamic: description
Dynamic: description-content-type
Dynamic: home-page
Dynamic: license-file
Dynamic: requires-dist
Dynamic: requires-python
Dynamic: summary
